forest_plot_data/__init__.py
forest_plot_data/common.py
forest_plot_data/forest_plot.ipynb
forest_plot_data/forest_plot_data.py
forest_plot_data-0.0.1.dist-info/LICENSE
forest_plot_data-0.0.1.dist-info/METADATA
forest_plot_data-0.0.1.dist-info/WHEEL
forest_plot_data-0.0.1.dist-info/entry_points.txt
forest_plot_data-0.0.1.dist-info/top_level.txt
forest_plot_data-0.0.1.dist-info/RECORD
