Metadata-Version: 2.2
Name: forest_plot_data
Version: 0.0.1
Summary: A Python package to extract plot-level variables from Google Earth Engine
Author-email: Tara Skiba <taraskibaemail@gmail.com>
License: MIT License
Project-URL: Homepage, https://github.com/npcbaddie/forest_plot_data
Keywords: forest_plot_data
Classifier: Intended Audience :: Developers
Classifier: License :: OSI Approved :: MIT License
Classifier: Natural Language :: English
Classifier: Programming Language :: Python :: 3.8
Classifier: Programming Language :: Python :: 3.9
Classifier: Programming Language :: Python :: 3.10
Classifier: Programming Language :: Python :: 3.11
Classifier: Programming Language :: Python :: 3.12
Requires-Python: >=3.8
License-File: LICENSE
Requires-Dist: numpy
Provides-Extra: all
Requires-Dist: forest_plot_data[extra]; extra == "all"
Provides-Extra: extra
Requires-Dist: pandas; extra == "extra"
